slizzy/__init__.py
slizzy/main.py
slizzy/tolerance.py
slizzy/track.py
slizzy/version.py
slizzy/beatport/__init__.py
slizzy/beatport/beatport.py
slizzy/config/__init__.py
slizzy/config/beatport.py
slizzy/config/configerror.py
slizzy/config/default.py
slizzy/config/google.py
slizzy/config/mp3co.py
slizzy/config/setup.py
slizzy/config/slider.py
slizzy/config/slizzy.py
slizzy/config/zippy.py
slizzy/downloader/__init__.py
slizzy/downloader/downloader.py
slizzy/google/__init__.py
slizzy/google/google.py
slizzy/mp3co/__init__.py
slizzy/mp3co/mp3co.py
slizzy/slider/__init__.py
slizzy/slider/slider.py
slizzy/util/__init__.py
slizzy/util/bytes.py
slizzy/util/color.py
slizzy/util/frange.py
slizzy/util/iterator.py
slizzy/util/math.py
slizzy/util/mp3.py
slizzy/util/os.py
slizzy/util/path.py
slizzy/util/string.py
slizzy/util/time.py
slizzy/util/types.py
slizzy/util/logging/__init__.py
slizzy/util/logging/level.py
slizzy/util/logging/log.py
slizzy/zippy/__init__.py
slizzy/zippy/zippy.py
slizzy-1.5.1.dist-info/LICENSE
slizzy-1.5.1.dist-info/METADATA
slizzy-1.5.1.dist-info/WHEEL
slizzy-1.5.1.dist-info/entry_points.txt
slizzy-1.5.1.dist-info/top_level.txt
slizzy-1.5.1.dist-info/RECORD
