Metadata-Version: 2.1
Name: slizzy
Version: 1.5.1
Summary: Slizzy is a program and a library to search for tracks and download slider.kz, mp3co.biz and zippyshare.com objects.
Home-page: https://www.github.com/gahag/slizzy
Author: gahag
Author-email: gabriel.s.b@live.com
License: UNKNOWN
Platform: UNKNOWN
Classifier: License :: OSI Approved :: BSD License
Classifier: Environment :: Console
Classifier: Programming Language :: Python :: 3
Classifier: Topic :: Utilities
Requires-Dist: beautifulsoup4
Requires-Dist: colorama
Requires-Dist: hsaudiotag3k
Requires-Dist: fuzzywuzzy
Requires-Dist: requests
Requires-Dist: python-Levenshtein
